{
    "name": "Global Information",
    "numberOfRequests": {
        "total": 4,
        "ok": 3,
        "ko": 1
    },
    "minResponseTime": {
        "total": 99,
        "ok": 99,
        "ko": 29111
    },
    "maxResponseTime": {
        "total": 29111,
        "ok": 741,
        "ko": 29111
    },
    "meanResponseTime": {
        "total": 7639,
        "ok": 482,
        "ko": 29111
    },
    "standardDeviation": {
        "total": 12399,
        "ok": 276,
        "ko": 0
    },
    "percentiles1": {
        "total": 674,
        "ok": 606,
        "ko": 29111
    },
    "percentiles2": {
        "total": 7834,
        "ok": 674,
        "ko": 29111
    },
    "percentiles3": {
        "total": 24855,
        "ok": 728,
        "ko": 29111
    },
    "percentiles4": {
        "total": 28260,
        "ok": 738,
        "ko": 29111
    },
    "group1": {
    "name": "t < 400 ms",
    "count": 1,
    "percentage": 25
},
    "group2": {
    "name": "400 ms < t < 1000 ms",
    "count": 2,
    "percentage": 50
},
    "group3": {
    "name": "t > 1000 ms",
    "count": 0,
    "percentage": 0
},
    "group4": {
    "name": "failed",
    "count": 1,
    "percentage": 25
},
    "meanNumberOfRequestsPerSecond": {
        "total": 0.11428571428571428,
        "ok": 0.08571428571428572,
        "ko": 0.02857142857142857
    }
}