{
    "name": "Global Information",
    "numberOfRequests": {
        "total": 4,
        "ok": 3,
        "ko": 1
    },
    "minResponseTime": {
        "total": 413,
        "ok": 413,
        "ko": 29773
    },
    "maxResponseTime": {
        "total": 29773,
        "ok": 6894,
        "ko": 29773
    },
    "meanResponseTime": {
        "total": 9627,
        "ok": 2911,
        "ko": 29773
    },
    "standardDeviation": {
        "total": 11890,
        "ok": 2847,
        "ko": 0
    },
    "percentiles1": {
        "total": 4160,
        "ok": 1426,
        "ko": 29773
    },
    "percentiles2": {
        "total": 12614,
        "ok": 4160,
        "ko": 29773
    },
    "percentiles3": {
        "total": 26341,
        "ok": 6347,
        "ko": 29773
    },
    "percentiles4": {
        "total": 29087,
        "ok": 6785,
        "ko": 29773
    },
    "group1": {
    "name": "t < 400 ms",
    "count": 0,
    "percentage": 0
},
    "group2": {
    "name": "400 ms < t < 1000 ms",
    "count": 1,
    "percentage": 25
},
    "group3": {
    "name": "t > 1000 ms",
    "count": 2,
    "percentage": 50
},
    "group4": {
    "name": "failed",
    "count": 1,
    "percentage": 25
},
    "meanNumberOfRequestsPerSecond": {
        "total": 0.09302325581395349,
        "ok": 0.06976744186046512,
        "ko": 0.023255813953488372
    }
}