{
    "name": "Global Information",
    "numberOfRequests": {
        "total": 4,
        "ok": 3,
        "ko": 1
    },
    "minResponseTime": {
        "total": 117,
        "ok": 117,
        "ko": 29093
    },
    "maxResponseTime": {
        "total": 29093,
        "ok": 1543,
        "ko": 29093
    },
    "meanResponseTime": {
        "total": 7801,
        "ok": 704,
        "ko": 29093
    },
    "standardDeviation": {
        "total": 12304,
        "ok": 609,
        "ko": 0
    },
    "percentiles1": {
        "total": 997,
        "ok": 451,
        "ko": 29093
    },
    "percentiles2": {
        "total": 8431,
        "ok": 997,
        "ko": 29093
    },
    "percentiles3": {
        "total": 24960,
        "ok": 1434,
        "ko": 29093
    },
    "percentiles4": {
        "total": 28266,
        "ok": 1521,
        "ko": 29093
    },
    "group1": {
    "name": "t < 400 ms",
    "count": 1,
    "percentage": 25
},
    "group2": {
    "name": "400 ms < t < 1000 ms",
    "count": 1,
    "percentage": 25
},
    "group3": {
    "name": "t > 1000 ms",
    "count": 1,
    "percentage": 25
},
    "group4": {
    "name": "failed",
    "count": 1,
    "percentage": 25
},
    "meanNumberOfRequestsPerSecond": {
        "total": 0.1111111111111111,
        "ok": 0.08333333333333333,
        "ko": 0.027777777777777776
    }
}